fh_pyinstrument/__init__.py
fh_pyinstrument/_modidx.py
fh_pyinstrument/core.py
fh_pyinstrument-0.0.2.dist-info/licenses/LICENSE
fh_pyinstrument-0.0.2.dist-info/METADATA
fh_pyinstrument-0.0.2.dist-info/WHEEL
fh_pyinstrument-0.0.2.dist-info/entry_points.txt
fh_pyinstrument-0.0.2.dist-info/top_level.txt
fh_pyinstrument-0.0.2.dist-info/RECORD
