Metadata-Version: 2.4
Name: fh-pyinstrument
Version: 0.0.2
Summary: Using pyinstrument to profile FastHTML apps
Home-page: https://github.com/answerdotai/fh-pyinstrument
Author: Daniel Roy Greenfeld
Author-email: drg@answer.ai
License: Apache Software License 2.0
Keywords: nbdev jupyter notebook python fasthtml
Classifier: Development Status :: 4 - Beta
Classifier: Intended Audience :: Developers
Classifier: Natural Language :: English
Classifier: Programming Language :: Python :: 3.7
Classifier: Programming Language :: Python :: 3.8
Classifier: Programming Language :: Python :: 3.9
Classifier: Programming Language :: Python :: 3.10
Classifier: Programming Language :: Python :: 3.11
Classifier: Programming Language :: Python :: 3.12
Classifier: License :: OSI Approved :: Apache Software License
Requires-Python: >=3.7
License-File: LICENSE
Requires-Dist: python-fasthtml
Requires-Dist: pyinstrument
Provides-Extra: dev
Dynamic: author
Dynamic: author-email
Dynamic: classifier
Dynamic: description
Dynamic: description-content-type
Dynamic: home-page
Dynamic: keywords
Dynamic: license
Dynamic: license-file
Dynamic: provides-extra
Dynamic: requires-dist
Dynamic: requires-python
Dynamic: summary
